MANIFEST.in
Makefile
README.rst
setup.py
Peon.egg-info/PKG-INFO
Peon.egg-info/SOURCES.txt
Peon.egg-info/dependency_links.txt
Peon.egg-info/entry_points.txt
Peon.egg-info/top_level.txt
peon/__init__.py
peon/peon.py
peon/stop.png
peon/tick.png