Metadata-Version: 1.0
Name: Peon
Version: 0.2
Summary: Peon is an auto-testing-like tool
Home-page: http://www.nonesofar.org
Author: Bernardo Heynemann
Author-email: heynemann@gmail.com
License: OSI
Keywords: Testing Notify
Platform: UNKNOWN
Classifier: Development Status :: 4 - Beta
Classifier: Intended Audience :: Developers
Classifier: License :: OSI Approved
Classifier: Natural Language :: English
Classifier: Operating System :: MacOS
Classifier: Operating System :: Microsoft :: Windows
Classifier: Operating System :: POSIX :: Linux
Classifier: Programming Language :: Python :: 2.5
Classifier: Programming Language :: Python :: 2.6
Classifier: Topic :: Software Development :: Quality Assurance
Classifier: Topic :: Software Development :: Testing
